{"title": "Did Nicolas Tesla describe cell phones in 1926?", "subtitle": "\"When the radio is applied perfectly, the whole Earth will turn into a huge brain,\" the ocloclastic thinker said was supposed to interview 1926.", "author": "Alex Kasprak", "date": "7 February 2021", "vclaim_id": "vclaim-sno-tesla-cell-phones-1926", "vclaim": "In 1926, the world and inventor Nicola Tesla described the future of \"when radio is applied ideally the entire Earth\" in a way that allows humans to communicate with each other immediately no matter how far they are.\""}