{
  "title": "Did \u2018Antifa\u2019 Recruit Protesters on Craigslist in Nebraska?",
  "subtitle": "\u201cWe are ANTIFA, and we're willing to pay up to 1,000 people $25 per hour for protester,\u201d one ad allegedly said.",
  "author": "Alex Kasprak",
  "date": "11 June 2020",
  "vclaim_id": "vclaim-sno-antifa-craigslist-nebraska",
  "vclaim": "\u201cAntifa\u201d posted an ad on the Lincoln, Nebraska, Craigslist website offering to pay protesters \u201cto cause as much chaos and destruction as possible.\u201d"
}