{
  "title": "Was a Student Suspended for Pretending to be Transgender to Use the Girls\u2019 Locker Room?",
  "subtitle": "A story about a high school student talking his way into showering with girls after gym class is a work of fiction.",
  "author": "Dan Evon",
  "date": "23 February 2018",
  "vclaim_id": "vclaim-sno-student-suspended-pretending-transgender-locker-room",
  "vclaim": "A high school student pretended to be transgender so that he could take showers in the girls' locker room during gym class."
}