{
  "title": "Did Joe Biden Lie About a Drunken Driver\u2019s Killing His Wife?",
  "subtitle": "A few weeks after Biden was first elected to the U.S. Senate, his wife and 1-year-old daughter were killed in an automobile accident while Christmas shopping.",
  "author": "David Mikkelson",
  "date": "28 September 2020",
  "vclaim_id": "vclaim-sno-biden-lie-wife-killed-drunk-driver",
  "vclaim": "Joe Biden lied in claiming that the accident that killed his wife and daughter involved a driver who had been drinking."
}