{
  "title": "Sarah Palin Calls to Boycott Mall of America Because \u2018Santa Was Always White in the Bible\u2019",
  "subtitle": "A story that the former Alaska governor called for the boycott after discovering that the mall had hired its first black Santa Claus is a hoax.",
  "author": "Kim LaCapria",
  "date": "5 December 2016",
  "vclaim_id": "vclaim-sno-sarah-palin-calls-boycott-mall-america-santa-always-white-bible",
  "vclaim": "Sarah Palin called for a Mall of America boycott over its hiring a black man to play Santa Claus."
}