{
  "title": "Target Transgender Bathroom Policy",
  "subtitle": "A social media controversy erupted when Target announced a chain-wide policy inviting transgender customers to use the bathroom that matched their gender identity.",
  "author": "Kim LaCapria",
  "date": "20 April 2016",
  "vclaim_id": "vclaim-sno-target-transgender-bathroom-policy",
  "vclaim": "Target caved to pressure from President Obama and LGBT groups and instituted a store-wide policy allowing transgender employees and shoppers to use the bathroom that matched their gender identity."
}