{"title": "Michigan farmers were forced to destroy edible cherry to support imports?", "subtitle": "Facebook virus about the excess cherry crops destroyed in the United States \"to make way for imports\" induces Lucafor but contains some mistakes.", "author": "Kim LaCapria", "date": "15 September 2016", "vclaim_id": "vclaim-sno-michigan-farmers-destroy-cherries", "vclaim": "A farmer in Michigan was forced to destroy 40,000 edible cherries to make room for cherry imported from outside the United States."}