{
  "title": "Did California Attempt to Force Parents to Accept a Curriculum That Teaches Children \u2018There Are 15 Genders\u2019?",
  "subtitle": "Conservative websites exploded into outrage at what they described as mandatory \"indoctrination sessions\" on gender identity for K-12 students.",
  "author": "Dan MacGuill",
  "date": "28 January 2019",
  "vclaim_id": "vclaim-sno-california-15-genders",
  "vclaim": "In 2019, California education authorities formulated a policy that, if implemented, would force parents to allow their children to be taught that \"there are 15 genders.\""
}