{
  "title": "Clinton Campaign Overcharging Poor Donors?",
  "subtitle": "Rumor claims the Hillary Clinton campaign is fraudulently overcharging the accounts of small donors, but the true nature and breadth of the issue is difficult to determine.",
  "author": "Kim LaCapria",
  "date": "16 September 2016",
  "vclaim_id": "vclaim-sno-clinton-campaign-overcharging-donors",
  "vclaim": "Hillary Clinton's campaign has been systemically overcharging small donors, including the elderly and poor people."
}