{
  "title": "Was Mike Pence at the White House During the U.S. Strike Against Syria?",
  "subtitle": "After she was criticized online, White House press secretary Sarah Huckabee Sanders said a photograph which included the traveling Vice President was not misleading.",
  "author": "Arturo Garcia",
  "date": "15 April 2018",
  "vclaim_id": "vclaim-sno-pence-white-house-syria-photo",
  "vclaim": "Vice President Mike Pence was in the White House Situation Room while the U.S. carried out a strike against Syria."
}