{
  "title": "Radioactive Canadian Salmon Tied to Fukushima Disaster?",
  "subtitle": "A single sockeye salmon found in a Canadian lake in 2015 did test positive for trace amounts of Fukushima radiation, but this is not a demonstrable health concern.",
  "author": "Alex Kasprak",
  "date": "7 March 2017",
  "vclaim_id": "vclaim-sno-radioactive-salmon-fukushima",
  "vclaim": "The first \"radioactive salmon\" attributed to the Fukushima nuclear disaster have been found in British Columbia, Canada, posing a risk to human health."
}