{
  "title": "Lesson in Compassion",
  "subtitle": "Was an actor disguised as a beggar used to test divinity students' compassion?",
  "author": "David Mikkelson",
  "date": "20 June 2011",
  "vclaim_id": "vclaim-sno-compassion-play",
  "vclaim": "Students at a religious institute enrolled in a class on the life of Jesus arrive at their classroom to take the final exam and find a notice informing them that the test will be given in another building on the other side of the campus. As the students rush across campus to the new room, each is accosted by a forlorn beggar who entreats their help. None of the students stops for him, however \u2014 they all rush by, anxious to arrive on time for the exam."
}