{
  "title": "NBC Accidentally Posts Election Results a Week Early",
  "subtitle": "In what is becoming a common pre-election conspiracy-driving glitch, an NBC affiliate's software test was interpreted as evidence election results were rigged.",
  "author": "Kim LaCapria",
  "date": "5 November 2016",
  "vclaim_id": "vclaim-sno-nbc-accidentally-posts-election-results-a-week-early",
  "vclaim": "Chattanooga-area NBC affiliate WRCB inadvertently exposed the rigging of 2016 election results in Hillary Clinton's favor."
}