{
  "title": "Did Captain Kangaroo and Lee Marvin Fight at Iwo Jima?",
  "subtitle": "Lee Marvin and Bob 'Captain Kangaroo' Keeshan were both in the military during World War II, but they didn't fight together at Iwo Jima or any other engagement.",
  "author": "David Mikkelson",
  "date": "8 March 2002",
  "vclaim_id": "vclaim-sno-captain-kangaroo-lee-marvin-iwo-jima",
  "vclaim": "Lee Marvin, actor, and Bob Keeshan, television's \"Captain Kangaroo\" were World War II veterans who fought together at Iwo Jima."
}