{
  "title": "Fines for Bringing Supplies to Standing Rock DAPL Protests",
  "subtitle": "Rumors that bringing supplies to protesters at the Standing Rock Reservation could carry a $1,000 fine are accurate, at least according to the Morton County Sheriff's Department.",
  "author": "Kim LaCapria",
  "date": "30 November 2016",
  "vclaim_id": "vclaim-sno-fines-for-bringing-supplies-to-standing-rock-dapl-protests",
  "vclaim": "Anyone bringing supplies to DAPL protesters at the Standing Rock Indian Reservation could be fined $1,000 for the attempt, according to the Morton County Sheriff's Department."
}