{"title": "How to Stop Obama in the Electoral College", "subtitle": "If voters from one third of the states refuse to vote in the Electoral College, the next President of the United States will choose the House of Representatives?", "author": "David Mikkelson", "date": "20 November 2012", "vclaim_id": "vclaim-sno-get-out-the-vote", "vclaim": "If voters from one third of the states refuse to vote in the Electoral College, the next President of the United States will be chosen the House of Representatives."}