{"url": "/factchecks/2020/nov/30/viral-image/no-denver-broncos-didnt-sign-colin-kaepernick/", "speaker": "Viral image", "vclaim": "Says the Denver Broncos signed Colin Kaepernick.", "truth_label": "false", "date": "stated on November 28, 2020 in a Facebook post:", "title": "No, the Denver Broncos didn\u2019t sign Colin Kaepernick", "text": "The Denver Broncos football team found themselves without a quarterback for their recent game against the New Orleans Saints after the league discovered some of the team\u2019s players had been maskless around another player who tested positive for COVID-19.\nBut the Broncos didn\u2019t quickly sign former San Francisco 49ers quarterback Colin Kaepernick to step in, as a recent Facebook post claimed.\n\"Breaking,\" the post said. \"Broncos signing Colin Kaepernick.\"\u00a0\nThis post was flagged as part of Facebook\u2019s efforts to combat false news and misinformation on its News Feed. (Read more about our partnership with Facebook.)\u00a0\nKaepernick, who led the 49ers to the Super Bowl XLVII in 2013, has not played in the NFL since the 2016 season, when he began protesting police violence against Black Americans by sitting or kneeling during the pregame national anthem. In 2019, he and the NFL settled a grievance alleging that the league and team owners colluded to keep him out of football.\n\nFeatured Fact-check\n\n\n\n\n\n\n\n\n\n\n\n\n\n\n\n\nFacebook posts\n\n\nstated on January 22, 2021 in a Facebook post\n\n\n\n\n\n\n\n\nHank Aaron\u2019s death was caused by a COVID-19 vaccine.\n\n\n\n\n\n\n\n\n\n\n\n\nBy Noah Y. Kim \u2022 January 26, 2021\n\n\n\n\n\n\n\nFor the Nov. 29 game against the Saints, the same COVID-19 protocols that prevented four eligible quarterbacks on the Broncos active roster from playing also precluded the team from signing Kaepernick.\u00a0\nNews broke on Nov. 28 that the quarterbacks wouldn\u2019t be able to play in the game the next day. It would have taken at least six days for Kaepernick to be eligible to play under the NFL\u2019s COVID-19 rules. New players must remain in isolation for six days before joining a team.\u00a0\nKendall Hinton, a practice squad receiver for the Broncos, filled in as quarterback on Nov. 29. The Broncos lost to the Saints 31-3.\nWe rate this Facebook post False.", "vclaim_id": "vclaim-pol-18581"}