{"title": "Does access to Lugo Wato guarantee free meals there for life?", "subtitle": "It's not a wise call to say that a lifetime supply of free food is not a good reason to get tattooed for a restaurant logo -- it just won't work.", "author": "Dan Evon", "date": "22 May 2018", "vclaim_id": "vclaim-sno-does-restaurant-tattoo-guarantee-food", "vclaim": "People who get tattoos of slogans from one of a variety of restaurants - such as McDonalds, Taco Bell, Chipotle - are guaranteed free food there for life."}