{"title": "Did Parkland's student kill Chris Williams while he was saving schoolmates?", "subtitle": "A student was shot while closing the door while shooting at the school -- but his name isn't Chris Williams, and he's not the one who was photographed at Facebook's viral site.", "author": "Kim LaCapria", "date": "19 February 2018", "vclaim_id": "vclaim-sno-chris-williams-parkland", "vclaim": "The photo depicts Chris Williams in high school, shooting nine times while protecting his fellow students, leaving him in critical condition."}