{"title": "Is Jerry Brown preparing to release 10,000 child molesters and rapists from prison?", "subtitle": "The conspiracy theory blog published an alarming story after the judge ruled on the effects of the new California law on sexual offenders.", "author": "Arturo Garcia", "date": "13 April 2018", "vclaim_id": "vclaim-sno-jerry-brown-preparing-release-10000-pedophiles-rapists-prison", "vclaim": "The Governor of California (Jerry Brown) will release 10,000 convicted sex offenders after the judge's ruling."}