{"title": "The Muslims gathered around the image of Jesus'cut head", "subtitle": "A misleading and fearsome video showing Muslims \"extremists\" gathered around a picture of Christ's head cut off on Facebook by preacher Michael Chetwood.", "author": "Dan Evon", "date": "25 June 2016", "vclaim_id": "vclaim-sno-muslims-rally-around-image-jesus-decapitated-head", "vclaim": "A video shows a group of Muslim \"extremists\" gathering around the headboard of the decapitated Christ in Dearborn, Michigan."}