{"title": "Did Hillary Clinton say: \" I would like to see people like Donald Trump running into the office '?", "subtitle": "\"In fact, when you say business men and women, I can only think of a particular man I would like to see running for president sometime in the future.\"", "author": "Dan Evon", "date": "28 October 2016", "vclaim_id": "vclaim-sno-people-like-donald-trump", "vclaim": ":: Hillary Clinton proposed during the 2013 speech that she would like to see Donald Trump run for President."}