{"title": "She's California Goff. Jerry Brown is moving the Veterans' Cemetery to make room for low-income housing?", "subtitle": "A notorious producer of junk news published Mimi fabricated about the transport of a military cemetery in California.", "author": "David Mikkelson", "date": "26 August 2018", "vclaim_id": "vclaim-sno-california-veterans-cemetery-modesto", "vclaim": "California Governor Jerry Brown moves the Veterans &apos; Cemetery from San Francisco to Modesto to make room for low-income housing."}