{"title": "Intelligence is only an inheritance from your mother?", "subtitle": "The viral news stories claimed that \"new research\" proved that your intelligence was inherited only from your mother. However, these stories did not in fact cite new research, but rather distorted the picture of the flag they used to make their allegations.", "author": "Alex Kasprak", "date": "11 October 2016", "vclaim_id": "vclaim-sno-intelligence-is-inherited-only-from-your-mother", "vclaim": "The intelligence of a person is genetically determined by the mother alone."}