{"title": "Did Mike Pines make Trump's supporters \"more than half of the women \" in March?", "subtitle": "A false Facebook account overestimated the number of conservatives who attended demonstrations around the world on 21 January 2017.", "author": "Arturo Garcia", "date": "24 January 2017", "vclaim_id": "vclaim-sno-mike-pence-conservatives-womens-march", "vclaim": "Vice President Mike Pines claimed that \"more than half\" of the people on the women's march in Washington supported President Donald Trump."}